cofybox_dce/__init__.py
cofybox_dce/abstract.py
cofybox_dce/factory.py
cofybox_dce/misc.py
cofybox_dce/pricing_collectors/__init__.py
cofybox_dce/pricing_collectors/belgium.py
cofybox_dce/pricing_collectors/france.py
cofybox_dce/pricing_collectors/octopus.py
cofybox_dce/pricing_collectors/octopus_outgoing_workaround.py
cofybox_dce/pricing_collectors/pricing.py
cofybox_dce/pricing_collectors/spain.py
cofybox_dce-0.0.12.dist-info/LICENSE
cofybox_dce-0.0.12.dist-info/METADATA
cofybox_dce-0.0.12.dist-info/WHEEL
cofybox_dce-0.0.12.dist-info/top_level.txt
cofybox_dce-0.0.12.dist-info/RECORD
