Metadata-Version: 2.1
Name: cofybox-dce
Version: 0.0.12
Summary: COFYCloud Data Collector Engine python code
Home-page: https://docs.cofybox.io
Author: Jan Pecinovsky
Author-email: jan@energieid.be
Project-URL: Bug Tracker, https://gitlab.com/rescoopvpp/cofybox-dce/-/issues
Classifier: Programming Language :: Python :: 3
Classifier: License :: OSI Approved :: MIT License
Classifier: Operating System :: OS Independent
Requires-Python: >=3.6
License-File: LICENSE
Requires-Dist: pandas (==1.4.0)
Requires-Dist: octopusagile (==0.0.6)
Requires-Dist: entsoe-py (==0.5.9)
Requires-Dist: aiopvpc (==4.2.1)
